FloriaTelegramBotAPI/Bot.py
FloriaTelegramBotAPI/Config.py
FloriaTelegramBotAPI/Enums.py
FloriaTelegramBotAPI/Extractor.py
FloriaTelegramBotAPI/Utils.py
FloriaTelegramBotAPI/Validator.py
FloriaTelegramBotAPI/WebClient.py
FloriaTelegramBotAPI/__init__.py
FloriaTelegramBotAPI/py.typed
FloriaTelegramBotAPI/Abc/Container.py
FloriaTelegramBotAPI/Abc/Event.py
FloriaTelegramBotAPI/Abc/Filter.py
FloriaTelegramBotAPI/Abc/Handler.py
FloriaTelegramBotAPI/Abc/Middleware.py
FloriaTelegramBotAPI/Abc/Mixin.py
FloriaTelegramBotAPI/Abc/Router.py
FloriaTelegramBotAPI/Abc/Storage.py
FloriaTelegramBotAPI/Abc/__init__.py
FloriaTelegramBotAPI/Events/Event.py
FloriaTelegramBotAPI/Events/__init__.py
FloriaTelegramBotAPI/Exceptions/ExceptionContainer.py
FloriaTelegramBotAPI/Exceptions/Exceptions.py
FloriaTelegramBotAPI/Exceptions/__init__.py
FloriaTelegramBotAPI/Filters/FilterContainer.py
FloriaTelegramBotAPI/Filters/Filters.py
FloriaTelegramBotAPI/Filters/__init__.py
FloriaTelegramBotAPI/Filters/CallbackFilters/Common.py
FloriaTelegramBotAPI/Filters/CallbackFilters/__init__.py
FloriaTelegramBotAPI/Filters/MessageFilters/Common.py
FloriaTelegramBotAPI/Filters/MessageFilters/__init__.py
FloriaTelegramBotAPI/Handlers/BaseHandler.py
FloriaTelegramBotAPI/Handlers/HandlerContainer.py
FloriaTelegramBotAPI/Handlers/Handlers.py
FloriaTelegramBotAPI/Handlers/__init__.py
FloriaTelegramBotAPI/MethodForms/Common.py
FloriaTelegramBotAPI/MethodForms/__init__.py
FloriaTelegramBotAPI/Middleware/BaseMiddleware.py
FloriaTelegramBotAPI/Middleware/__init__.py
FloriaTelegramBotAPI/Protocols/Functions.py
FloriaTelegramBotAPI/Protocols/__init__.py
FloriaTelegramBotAPI/Router/Router.py
FloriaTelegramBotAPI/Router/RouterContainer.py
FloriaTelegramBotAPI/Router/__init__.py
FloriaTelegramBotAPI/SmartTypes/CallbackQuery.py
FloriaTelegramBotAPI/SmartTypes/ChatAction.py
FloriaTelegramBotAPI/SmartTypes/CommandArgs.py
FloriaTelegramBotAPI/SmartTypes/Message.py
FloriaTelegramBotAPI/SmartTypes/TextFormat.py
floriatelegrambotapi-0.3.2.1.dist-info/licenses/LICENSE
floriatelegrambotapi-0.3.2.1.dist-info/METADATA
floriatelegrambotapi-0.3.2.1.dist-info/WHEEL
floriatelegrambotapi-0.3.2.1.dist-info/top_level.txt
floriatelegrambotapi-0.3.2.1.dist-info/zip-safe
floriatelegrambotapi-0.3.2.1.dist-info/RECORD
