Metadata-Version: 2.4
Name: FloriaTelegramBotAPI
Version: 0.3.2.1
Summary: Python Telegram Bot API
Author: FloriaProduction
Author-email: FloriaProduction@yandex.ru
License: Apache-2.0
Project-URL: Source, https://github.com/FloriaProduction/FloriaTelegramBotAPI
Keywords: python api telegram bot tools
Classifier: Programming Language :: Python :: 3.12
Classifier: License :: OSI Approved :: Apache Software License
Classifier: Environment :: Console
Classifier: Intended Audience :: Developers
Classifier: Typing :: Typed
Requires-Python: >=3.12
License-File: LICENSE
Requires-Dist: httpx
Requires-Dist: pydantic
Requires-Dist: schedule
Requires-Dist: mmh3
Dynamic: author
Dynamic: author-email
Dynamic: classifier
Dynamic: description
Dynamic: description-content-type
Dynamic: keywords
Dynamic: license
Dynamic: license-file
Dynamic: project-url
Dynamic: requires-dist
Dynamic: requires-python
Dynamic: summary
